<?xml version="1.0" encoding="UTF-8"?>
<OAI-PMH xmlns="http://www.openarchives.org/OAI/2.0/" xmlns:xsi="http://www.w3.org/2001/XMLSchema-instance" xsi:schemaLocation="http://www.openarchives.org/OAI/2.0/ http://www.openarchives.org/OAI/2.0/OAI-PMH.xsd">
<responseDate>2020-04-11T23:58:28Z</responseDate>
<request verb="ListRecords" until="2017-01-08" from="2017-01-08" metadataPrefix="arXiv" set="physics">http://export.arxiv.org/oai2</request>
<ListRecords>
<record>
<header>
 <identifier>oai:arXiv.org:1112.2276</identifier>
 <datestamp>2017-01-08</datestamp>
 <setSpec>physics</setSpec>
</header>
<metadata>
 <arXiv xmlns="http://arxiv.org/OAI/arXiv/" xmlns:xsi="http://www.w3.org/2001/XMLSchema-instance" xsi:schemaLocation="http://arxiv.org/OAI/arXiv/ http://arxiv.org/OAI/arXiv.xsd">
 <id>1112.2276</id><created>2011-12-10</created><authors><author><keyname>Freire</keyname><forenames>Manuel J.</forenames></author><author><keyname>Lopez</keyname><forenames>Marcos A.</forenames></author><author><keyname>Algarin</keyname><forenames>Jose M.</forenames></author><author><keyname>Breuer</keyname><forenames>Felix</forenames></author><author><keyname>Marqu&#xe9;s</keyname><forenames>Ricardo</forenames></author></authors><title>Image acceleration in parallel magnetic resonance imaging by means of
  metamaterial magnetoinductive lenses</title><categories>physics.med-ph</categories><comments>10 pages, 4 figures</comments><license>http://arxiv.org/licenses/nonexclusive-distrib/1.0/</license><abstract>  Parallel magnetic resonance imaging (MRI) is a technique of image
acceleration which takes advantage of the localization of the field of view
(FOV) of coils in an array. In this letter we show that metamaterial lenses
based on capacitively-loaded rings can provide higher localization of the FOV.
Several lens designs are systematically analyzed in order to find the structure
providing higher signal-to-noise-ratio. The magnetoinductive (MI) lens is find
to be the optimum structure and an experiment is developed to show it. The
ability of the fabricated MI lenses to accelerate the image is quantified by
means of the parameter known in the MRI community as g-factor.
</abstract></arXiv>
</metadata>
</record>
<record>
<header>
 <identifier>oai:arXiv.org:1207.0425</identifier>
 <datestamp>2017-01-08</datestamp>
 <setSpec>physics</setSpec>
</header>
<metadata>
 <arXiv xmlns="http://arxiv.org/OAI/arXiv/" xmlns:xsi="http://www.w3.org/2001/XMLSchema-instance" xsi:schemaLocation="http://arxiv.org/OAI/arXiv/ http://arxiv.org/OAI/arXiv.xsd">
 <id>1207.0425</id><created>2012-07-02</created><authors><author><keyname>Amphawan</keyname><forenames>Angela</forenames></author><author><keyname>Khair</keyname><forenames>Mohd Amirol Md</forenames></author><author><keyname>Hasan</keyname><forenames>Hassanuddin</forenames></author></authors><title>Multimedia Traffic Routing in Multilayer WDM Networks</title><categories>cs.NI physics.optics</categories><comments>10 pages, 8 figures</comments><journal-ref>Multimedia Traffic Routing in Multilayer WDM Networks&quot;, Network
  and Complex Systems, Vol. 2, No. 3, pp. 1 - 9, 2012, ISSN 2224-610X (Paper)
  ISSN 2225-0603 (Online)</journal-ref><license>http://arxiv.org/licenses/nonexclusive-distrib/1.0/</license><abstract>  The advent of real-time multimedia services over the Internet has stimulated
new technologies for expanding the information carrying capacity of optical
network backbones. Multilayer wavelength division multiplexing (WDM) packet
switching is an emerging technology for increasing the bandwidth of optical
networks. Two algorithms for the routing of the multimedia traffic flows were
applied: (i) Capacitated Shortest Path First (CSPF) routing, which minimizes
the distance of each flow linking the given source and destination nodes and
satisfying capacity constraints; and (ii) Flow Deviation Algorithm (FDA)
routing, which minimizes the network-wide average packet delay.
</abstract></arXiv>
</metadata>
</record>
<record>
<header>
 <identifier>oai:arXiv.org:1308.0110</identifier>
 <datestamp>2017-01-08</datestamp>
 <setSpec>physics</setSpec>
</header>
<metadata>
 <arXiv xmlns="http://arxiv.org/OAI/arXiv/" xmlns:xsi="http://www.w3.org/2001/XMLSchema-instance" xsi:schemaLocation="http://arxiv.org/OAI/arXiv/ http://arxiv.org/OAI/arXiv.xsd">
 <id>1308.0110</id><created>2013-08-01</created><updated>2013-08-21</updated><authors><author><keyname>U</keyname><forenames>Satya Sainadh</forenames></author><author><keyname>Narayanan</keyname><forenames>Andal</forenames></author></authors><title>A mechanical switch for state transfer in dual cavity optomechanical
  systems</title><categories>quant-ph</categories><comments>Accepted in Physical Review A</comments><doi>10.1103/PhysRevA.88.033802</doi><license>http://arxiv.org/licenses/nonexclusive-distrib/1.0/</license><abstract>  Dual cavity opto-electromechanical systems (OEMS) are those where two
electromagnetic cavities are connected by a common mechanical spring. These
systems have been shown to facilitate high fidelity quantum state transfer from
one cavity to another. In this paper, we explicitly calculate the effect on the
fidelity of state transfer, when an additional spring is attached to only one
of the cavities. Our quantitative estimates of loss of fidelity, highlight the
sensitivity of dual cavity OEMS when it couples to additional mechanical modes.
We show that this sensitivity can be used to design an effective mechanical
switch, for inhibition or high fidelity transmission of quantum states between
the cavities.
</abstract></arXiv>
</metadata>
</record>
<record>
<header>
 <identifier>oai:arXiv.org:1311.0123</identifier>
 <datestamp>2017-01-08</datestamp>
 <setSpec>physics</setSpec>
</header>
<metadata>
 <arXiv xmlns="http://arxiv.org/OAI/arXiv/" xmlns:xsi="http://www.w3.org/2001/XMLSchema-instance" xsi:schemaLocation="http://arxiv.org/OAI/arXiv/ http://arxiv.org/OAI/arXiv.xsd">
 <id>1311.0123</id><created>2013-11-01</created><updated>2014-02-05</updated><authors><author><keyname>Borlenghi</keyname><forenames>Simone</forenames></author><author><keyname>Lepri</keyname><forenames>Stefano</forenames></author><author><keyname>Bergqvist</keyname><forenames>Lars</forenames></author><author><keyname>Delin</keyname><forenames>Anna</forenames></author></authors><title>Thermo-magnonic diode: rectification of energy and magnetization
  currents</title><categories>cond-mat.mes-hall</categories><comments>7 pages, 8 figures</comments><doi>10.1103/PhysRevB.89.054428</doi><license>http://arxiv.org/licenses/nonexclusive-distrib/1.0/</license><abstract>  We investigate the dynamics of two coupled macrospins connected to thermal
baths at different temperatures. The system behaves like a diode which allows
the propagation of energy and mag- netization currents in one direction only.
This effect is described by a simple model of two coupled nonlinear oscillators
interacting with two independent reservoirs. It is shown that the rectification
phenomenon can be interpreted as a a stochastic phase synchronization of the
two spin-oscillators. A brief comparison with realistic micromagnetic
simulations is presented. This new effect yields promising opportunities in
spin-caloritronics devices.
</abstract></arXiv>
</metadata>
</record>
</ListRecords>
</OAI-PMH>
